README.md
setup.cfg
setup.py
heptools/__init__.py
heptools/entry.py
heptools.egg-info/PKG-INFO
heptools.egg-info/SOURCES.txt
heptools.egg-info/dependency_links.txt
heptools.egg-info/entry_points.txt
heptools.egg-info/requires.txt
heptools.egg-info/top_level.txt