Metadata-Version: 1.0
Name: heptools
Version: 1.0
Summary: Command line Tool for HEP.
Home-page: https://github.com/xiawu/hep-tools
Author: xiawu
Author-email: xiawu@zeuux.org
License: UNKNOWN
Platform: UNKNOWN
